FirstHomework_package_Olesja_Tsimmerman/FirstHomeworkTask1.py
FirstHomework_package_Olesja_Tsimmerman/__init__.py
FirstHomework_package_Olesja_Tsimmerman-0.0.2.dist-info/LICENSE
FirstHomework_package_Olesja_Tsimmerman-0.0.2.dist-info/METADATA
FirstHomework_package_Olesja_Tsimmerman-0.0.2.dist-info/WHEEL
FirstHomework_package_Olesja_Tsimmerman-0.0.2.dist-info/top_level.txt
FirstHomework_package_Olesja_Tsimmerman-0.0.2.dist-info/RECORD
