Metadata-Version: 2.1
Name: FirstHomework_package_Olesja_Tsimmerman
Version: 0.0.2
Summary: A first package
Author-email: Olesja Tsimmerman <oltsim@taltech.ee>
Project-URL: Homepage, https://github.com/pypa/sampleproject
Project-URL: Issues, https://github.com/pypa/sampleproject/issues
Classifier: Programming Language :: Python :: 3
Classifier: License :: OSI Approved :: MIT License
Classifier: Operating System :: OS Independent
Requires-Python: >=3.8
License-File: LICENSE
